demommath/__init__.py
demommath/addsub/__init__.py
demommath/addsub/addas.py
demommath/calculations/LCM_of_num.py
demommath/calculations/__init__.py
demommath/calculations/calc.py
demommath/calculations/mean_of_num.py
demommath/factorials/__init__.py
demommath/factorials/fact.py
demommath/multidiv/__init__.py
demommath/multidiv/md.py
demommath/odd_even/__init__.py
demommath/odd_even/evod.py
demommath/prime_num/__init__.py
demommath/prime_num/prime_no.py
demommath/sumarray/__init__.py
demommath/sumarray/addarray.py
demommath/sumarray/testing.py
demommath-0.1.9.dist-info/METADATA
demommath-0.1.9.dist-info/WHEEL
demommath-0.1.9.dist-info/entry_points.txt
demommath-0.1.9.dist-info/top_level.txt
demommath-0.1.9.dist-info/RECORD
